[
 {
  "title": "Swiss to vote on nationwide fireworks restrictions",
  "url": "https://www.reddit.com/r/europe/comments/1ug3fk5/swiss_to_vote_on_nationwide_fireworks_restrictions/",
  "source": "Reddit",
  "term": "Swiss",
  "date": ""
 },
 {
  "title": "This Cat Parasite Infects Billions of People. Scientists Say We’ve Been Underestimating It | Toxoplasma gondii, a.k.a. toxo, is a major cause of vision loss and other serious complications, and it may even alter people's behavior.",
  "url": "https://www.reddit.com/r/science/comments/1ug3d02/this_cat_parasite_infects_billions_of_people/",
  "source": "Reddit",
  "term": "Cat Parasite Infects",
  "date": ""
 },
 {
  "title": "Greece Army officer swore his military oath in the name of the Olympian Gods",
  "url": "https://www.reddit.com/r/europe/comments/1ug34ip/greece_army_officer_swore_his_military_oath_in/",
  "source": "Reddit",
  "term": "Greece Army",
  "date": ""
 },
 {
  "title": "Whole of France divided over ‘right-wing’ airconditioning amid sweltering heatwave | news.com.au",
  "url": "https://www.reddit.com/r/worldnews/comments/1ug2sgp/whole_of_france_divided_over_rightwing/",
  "source": "Reddit",
  "term": "Whole",
  "date": ""
 },
 {
  "title": "Always On Watch: Royal Navy maintains constant shadowing of Russian warships in UK waters",
  "url": "https://www.reddit.com/r/europe/comments/1ug2scb/always_on_watch_royal_navy_maintains_constant/",
  "source": "Reddit",
  "term": "Always",
  "date": ""
 },
 {
  "title": "The Ukrainian city of Lviv has failed to pay a Polish company millions of euros for the construction of a waste processing plant. The Polish firm has already won seven arbitration proceedings in European institutions, yet the money remains unpaid.",
  "url": "https://www.reddit.com/r/europe/comments/1ug2ghn/the_ukrainian_city_of_lviv_has_failed_to_pay_a/",
  "source": "Reddit",
  "term": "Ukrainian",
  "date": ""
 },
 {
  "title": "UK announces $380 million Ukraine support package ahead of key recovery conference",
  "url": "https://www.reddit.com/r/europe/comments/1ug2adf/uk_announces_380_million_ukraine_support_package/",
  "source": "Reddit",
  "term": "Ukraine",
  "date": ""
 },
 {
  "title": "Polish and Ukrainian companies will manufacture jet engines in Poland",
  "url": "https://www.reddit.com/r/europe/comments/1ug1x7m/polish_and_ukrainian_companies_will_manufacture/",
  "source": "Reddit",
  "term": "Polish",
  "date": ""
 },
 {
  "title": "More Abrams tanks have arrived to Poland",
  "url": "https://www.reddit.com/r/europe/comments/1ug1ozi/more_abrams_tanks_have_arrived_to_poland/",
  "source": "Reddit",
  "term": "More Abrams",
  "date": ""
 },
 {
  "title": "Cardiac arrests in London jump by third during heatwave as temperatures soar on Tube, says ambulance boss",
  "url": "https://www.reddit.com/r/europe/comments/1ug2i0o/cardiac_arrests_in_london_jump_by_third_during/",
  "source": "Reddit",
  "term": "Cardiac",
  "date": ""
 }
]